[
    {
        "user_id": "user_0",
        "name": "User0",
        "weights": {
            "Math": 1.26,
            "Physique": 0.52,
            "Psycho": 1.3,
            "Medecine": 1.03,
            "Histoire": 2.92,
            "Geographie": 4.01,
            "Geologie": 3.13,
            "Informatique": 1.07,
            "Art": 1.93
        },
        "history": [
            "article_157",
            "article_181",
            "article_183",
            "article_23",
            "article_37",
            "article_0"
        ],
        "mastery": {
            "Math": 3,
            "Physique": 2,
            "Psycho": 2,
            "Medecine": 1,
            "Histoire": 1,
            "Geographie": 3,
            "Geologie": 2,
            "Informatique": 3,
            "Art": 3
        }
    },
    {
        "user_id": "user_1",
        "name": "User1",
        "weights": {
            "Math": 2.82,
            "Physique": 1.88,
            "Psycho": 1.11,
            "Medecine": 0.92,
            "Histoire": 2.81,
            "Geographie": 2.26,
            "Geologie": 0.69,
            "Informatique": 2.01,
            "Art": 0.97
        },
        "history": [
            "article_35"
        ],
        "mastery": {
            "Math": 3,
            "Physique": 2,
            "Psycho": 2,
            "Medecine": 2,
            "Histoire": 3,
            "Geographie": 3,
            "Geologie": 1,
            "Informatique": 3,
            "Art": 1
        }
    },
    {
        "user_id": "user_2",
        "name": "User2",
        "weights": {
            "Math": 2.64,
            "Physique": 1.51,
            "Psycho": 2.36,
            "Medecine": 1.16,
            "Histoire": 1.97,
            "Geographie": 0.86,
            "Geologie": 1.92,
            "Informatique": 1.5,
            "Art": 1.32
        },
        "history": [],
        "mastery": {
            "Math": 1,
            "Physique": 1,
            "Psycho": 2,
            "Medecine": 3,
            "Histoire": 3,
            "Geographie": 2,
            "Geologie": 1,
            "Informatique": 1,
            "Art": 2
        }
    },
    {
        "user_id": "user_3",
        "name": "User3",
        "weights": {
            "Math": 0.71,
            "Physique": 1.99,
            "Psycho": 1.07,
            "Medecine": 1.14,
            "Histoire": 1.25,
            "Geographie": 0.57,
            "Geologie": 1.83,
            "Informatique": 1.26,
            "Art": 0.87
        },
        "history": [],
        "mastery": {
            "Math": 3,
            "Physique": 3,
            "Psycho": 3,
            "Medecine": 2,
            "Histoire": 2,
            "Geographie": 1,
            "Geologie": 1,
            "Informatique": 1,
            "Art": 3
        }
    },
    {
        "user_id": "user_4",
        "name": "User4",
        "weights": {
            "Math": 0.76,
            "Physique": 2.64,
            "Psycho": 3.15,
            "Medecine": 1.73,
            "Histoire": 1.43,
            "Geographie": 2.32,
            "Geologie": 2.74,
            "Informatique": 2.45,
            "Art": 1.54
        },
        "history": [
            "article_7",
            "article_17",
            "article_18",
            "article_19",
            "article_21"
        ],
        "mastery": {
            "Math": 2,
            "Physique": 1,
            "Psycho": 1,
            "Medecine": 2,
            "Histoire": 3,
            "Geographie": 3,
            "Geologie": 1,
            "Informatique": 2,
            "Art": 1
        }
    },
    {
        "user_id": "user_5",
        "name": "User5",
        "weights": {
            "Math": 0.96,
            "Physique": 1.07,
            "Psycho": 1.39,
            "Medecine": 1.32,
            "Histoire": 1.37,
            "Geographie": 2.24,
            "Geologie": 0.64,
            "Informatique": 1.75,
            "Art": 0.68
        },
        "history": [],
        "mastery": {
            "Math": 2,
            "Physique": 1,
            "Psycho": 2,
            "Medecine": 1,
            "Histoire": 1,
            "Geographie": 1,
            "Geologie": 2,
            "Informatique": 1,
            "Art": 3
        }
    },
    {
        "user_id": "user_6",
        "name": "User6",
        "weights": {
            "Math": 1.04,
            "Physique": 2.4,
            "Psycho": 1.93,
            "Medecine": 2.64,
            "Histoire": 0.53,
            "Geographie": 0.48,
            "Geologie": 2.44,
            "Informatique": 2.23,
            "Art": 1.43
        },
        "history": [],
        "mastery": {
            "Math": 2,
            "Physique": 2,
            "Psycho": 1,
            "Medecine": 3,
            "Histoire": 1,
            "Geographie": 2,
            "Geologie": 3,
            "Informatique": 3,
            "Art": 3
        }
    },
    {
        "user_id": "user_7",
        "name": "User7",
        "weights": {
            "Math": 1.93,
            "Physique": 2.42,
            "Psycho": 2.04,
            "Medecine": 1.06,
            "Histoire": 1.04,
            "Geographie": 2.29,
            "Geologie": 0.5,
            "Informatique": 1.33,
            "Art": 0.78
        },
        "history": [],
        "mastery": {
            "Math": 1,
            "Physique": 3,
            "Psycho": 2,
            "Medecine": 2,
            "Histoire": 3,
            "Geographie": 3,
            "Geologie": 2,
            "Informatique": 1,
            "Art": 3
        }
    },
    {
        "user_id": "user_8",
        "name": "User8",
        "weights": {
            "Math": 1.72,
            "Physique": 2.81,
            "Psycho": 1.93,
            "Medecine": 1.2,
            "Histoire": 2.22,
            "Geographie": 1.71,
            "Geologie": 1.13,
            "Informatique": 0.88,
            "Art": 1.2
        },
        "history": [],
        "mastery": {
            "Math": 1,
            "Physique": 3,
            "Psycho": 1,
            "Medecine": 3,
            "Histoire": 1,
            "Geographie": 2,
            "Geologie": 3,
            "Informatique": 2,
            "Art": 1
        }
    },
    {
        "user_id": "user_9",
        "name": "User9",
        "weights": {
            "Math": 1.7,
            "Physique": 2.17,
            "Psycho": 2.65,
            "Medecine": 2.45,
            "Histoire": 2.21,
            "Geographie": 2.17,
            "Geologie": 1.37,
            "Informatique": 2.7,
            "Art": 0.57
        },
        "history": [],
        "mastery": {
            "Math": 2,
            "Physique": 1,
            "Psycho": 1,
            "Medecine": 1,
            "Histoire": 3,
            "Geographie": 2,
            "Geologie": 3,
            "Informatique": 3,
            "Art": 1
        }
    }
]